odoo8_addon_website_event_register_free_with_sale-8.0.1.1.0-py2.7-nspkg.pth
odoo_addons/website_event_register_free_with_sale/__openerp__.py
odoo_addons/website_event_register_free_with_sale/__init__.py
odoo_addons/website_event_register_free_with_sale/exceptions.py
odoo_addons/website_event_register_free_with_sale/README.rst
odoo_addons/website_event_register_free_with_sale/templates/website_sale.xml
odoo_addons/website_event_register_free_with_sale/i18n/ru.po
odoo_addons/website_event_register_free_with_sale/i18n/it.po
odoo_addons/website_event_register_free_with_sale/i18n/es.po
odoo_addons/website_event_register_free_with_sale/i18n/ca.po
odoo_addons/website_event_register_free_with_sale/i18n/sl.po
odoo_addons/website_event_register_free_with_sale/i18n/de.po
odoo_addons/website_event_register_free_with_sale/i18n/fr.po
odoo_addons/website_event_register_free_with_sale/i18n/pt_BR.po
odoo_addons/website_event_register_free_with_sale/i18n/el_GR.po
odoo_addons/website_event_register_free_with_sale/i18n/fi.po
odoo_addons/website_event_register_free_with_sale/i18n/hr_HR.po
odoo_addons/website_event_register_free_with_sale/controllers/website_sale.py
odoo_addons/website_event_register_free_with_sale/controllers/website_event.py
odoo_addons/website_event_register_free_with_sale/controllers/__init__.py
odoo_addons/website_event_register_free_with_sale/static/description/icon.png
odoo8_addon_website_event_register_free_with_sale-8.0.1.1.0.dist-info/top_level.txt
odoo8_addon_website_event_register_free_with_sale-8.0.1.1.0.dist-info/WHEEL
odoo8_addon_website_event_register_free_with_sale-8.0.1.1.0.dist-info/RECORD
odoo8_addon_website_event_register_free_with_sale-8.0.1.1.0.dist-info/metadata.json
odoo8_addon_website_event_register_free_with_sale-8.0.1.1.0.dist-info/DESCRIPTION.rst
odoo8_addon_website_event_register_free_with_sale-8.0.1.1.0.dist-info/METADATA
odoo8_addon_website_event_register_free_with_sale-8.0.1.1.0.dist-info/namespace_packages.txt
